rncryptor.py
rncryptor-3.3.0.dist-info/LICENSE
rncryptor-3.3.0.dist-info/METADATA
rncryptor-3.3.0.dist-info/WHEEL
rncryptor-3.3.0.dist-info/top_level.txt
rncryptor-3.3.0.dist-info/RECORD
