Metadata-Version: 1.1
Name: rncryptor
Version: 3.3.0
Summary: Python implementation of RNCryptor
Home-page: https://github.com/RNCryptor/RNCryptor-python
Author: Yan Kalchevskiy
Author-email: yan.kalchevskiy@gmail.com
License: MIT
Keywords: RNCryptor cryptography
Platform: UNKNOWN
Classifier: Development Status :: 5 - Production/Stable
Classifier: Environment :: Console
Classifier: Intended Audience :: Developers
Classifier: License :: OSI Approved :: MIT License
Classifier: Programming Language :: Python :: 2
Classifier: Programming Language :: Python :: 2.7
Classifier: Programming Language :: Python :: 3
Classifier: Programming Language :: Python :: 3.4
Classifier: Programming Language :: Python :: 3.5
Classifier: Programming Language :: Python :: 3.6
Classifier: Programming Language :: Python :: Implementation :: CPython
Classifier: Topic :: Security :: Cryptography
